anti_cf/__init__.py
anti_cf/_constants.py
anti_cf/_flaresolverr.py
anti_cf/_persistent_session.py
anti_cf-1.1.2.dist-info/METADATA
anti_cf-1.1.2.dist-info/WHEEL
anti_cf-1.1.2.dist-info/RECORD
