Metadata-Version: 2.4
Name: anti_cf
Version: 1.1.2
Summary: Anti-CloudFlare package
License: MIT
Author: Steven Van Ingelgem
Author-email: steven@vaningelgem.be
Requires-Python: >=3.11,<4.0
Classifier: License :: OSI Approved :: MIT License
Classifier: Programming Language :: Python :: 3
Classifier: Programming Language :: Python :: 3.11
Classifier: Programming Language :: Python :: 3.12
Classifier: Programming Language :: Python :: 3.13
Classifier: Programming Language :: Python :: 3.14
Requires-Dist: fake-useragent
Requires-Dist: logprise
Requires-Dist: requests
